<?xml version="1.0" encoding="UTF-8"?>
<Students>
<Student><FirstName>Noellyn</FirstName><LastName>Earp</LastName><DateOfBirth>20.8.2005</DateOfBirth></Student><Student><FirstName>Maureen</FirstName><LastName>Knapton</LastName><DateOfBirth>24.7.2001</DateOfBirth></Student><Student><FirstName>Walliw</FirstName><LastName>Tomsu</LastName><DateOfBirth>8.10.2000</DateOfBirth></Student><Student><FirstName>Tyrus</FirstName><LastName>Boshers</LastName><DateOfBirth>22.9.2002</DateOfBirth></Student><Student><FirstName>Doralyn</FirstName><LastName>Crumpton</LastName><DateOfBirth>11.5.2003</DateOfBirth></Student><Student><FirstName>Crosby</FirstName><LastName>Penrith</LastName><DateOfBirth>30.12.2000</DateOfBirth></Student><Student><FirstName>Karena</FirstName><LastName>Batters</LastName><DateOfBirth>7.4.1999</DateOfBirth></Student><Student><FirstName>Humfried</FirstName><LastName>Michelotti</LastName><DateOfBirth>17.9.2002</DateOfBirth></Student><Student><FirstName>Noellyn</FirstName><LastName>Benedito</LastName><DateOfBirth>8.2.2001</DateOfBirth></Student><Student><FirstName>Grace</FirstName><LastName>Rief</LastName><DateOfBirth>10.9.2004</DateOfBirth></Student></Students>